chemicalchecker/__init__.py
chemicalchecker/core/__init__.py
chemicalchecker/core/char.py
chemicalchecker/core/chemcheck.py
chemicalchecker/core/clus.py
chemicalchecker/core/data.py
chemicalchecker/core/diagnostics.py
chemicalchecker/core/examples.py
chemicalchecker/core/molkit.py
chemicalchecker/core/neig.py
chemicalchecker/core/preprocess.py
chemicalchecker/core/proj.py
chemicalchecker/core/sign0.py
chemicalchecker/core/sign1.py
chemicalchecker/core/sign2.py
chemicalchecker/core/sign3.py
chemicalchecker/core/sign4.py
chemicalchecker/core/signature_base.py
chemicalchecker/core/signature_data.py
chemicalchecker/core/validation.py
chemicalchecker/core/examples/ctrp_auc.csv
chemicalchecker/core/examples/fps.pkl
chemicalchecker/core/examples/pharmacodb_targets.tsv
chemicalchecker/core/examples/toy_matrix.pkl
chemicalchecker/core/examples/toy_pairs.pkl
chemicalchecker/core/examples/validation_sets/atc_validation.tsv
chemicalchecker/core/examples/validation_sets/moa_validation.tsv
chemicalchecker/core/projector/__init__.py
chemicalchecker/core/projector/default.py
chemicalchecker/core/projector/pca.py
chemicalchecker/core/projector/tsne.py
chemicalchecker/core/projector/umap_.py
chemicalchecker/database/__init__.py
chemicalchecker/database/calcdata.py
chemicalchecker/database/database.py
chemicalchecker/database/dataset.py
chemicalchecker/database/datasource.py
chemicalchecker/database/molecule.py
chemicalchecker/database/molrepo.py
chemicalchecker/database/pubchem.py
chemicalchecker/database/uniprotkb.py
chemicalchecker/tool/__init__.py
chemicalchecker/tool/adanet/__init__.py
chemicalchecker/tool/adanet/adanet_wrap.py
chemicalchecker/tool/adanet/cnn_generator.py
chemicalchecker/tool/adanet/dnn_extend_generator.py
chemicalchecker/tool/adanet/dnn_stack_generator.py
chemicalchecker/tool/autoencoder/__init__.py
chemicalchecker/tool/autoencoder/autoencoder.py
chemicalchecker/tool/autoencoder/autoencoder_siamese.py
chemicalchecker/tool/cc_charts/char_utils/fisher.py
chemicalchecker-1.0.6.dist-info/AUTHORS.rst
chemicalchecker-1.0.6.dist-info/LICENSE
chemicalchecker-1.0.6.dist-info/METADATA
chemicalchecker-1.0.6.dist-info/WHEEL
chemicalchecker-1.0.6.dist-info/top_level.txt
chemicalchecker-1.0.6.dist-info/RECORD
