Metadata-Version: 2.1
Name: chemicalchecker
Version: 1.0.6
Summary: Chemical Checker Package.
Home-page: http://gitlabsbnb.irbbarcelona.org/packages/chemical_checker
Author: SBNB
Author-email: sbnb@irbbarcelona.org
License: MIT License
Keywords: chemicalchecker bioactivity signatures chemoinformatics
Classifier: Development Status :: 5 - Production/Stable
Classifier: Intended Audience :: Science/Research
Classifier: License :: OSI Approved :: MIT License
Classifier: Programming Language :: Python :: 2
Classifier: Programming Language :: Python :: 2.7
Classifier: Programming Language :: Python :: 3
Classifier: Programming Language :: Python :: 3.4
Classifier: Programming Language :: Python :: 3.5
Classifier: Programming Language :: Python :: 3.6
Classifier: Programming Language :: Python :: 3.7
Classifier: Programming Language :: Python :: 3.9
Classifier: Programming Language :: Python :: 3.10
Classifier: Operating System :: OS Independent
Classifier: Topic :: Scientific/Engineering :: Bio-Informatics
Classifier: Topic :: Scientific/Engineering :: Chemistry
Classifier: Topic :: Scientific/Engineering :: Artificial Intelligence
License-File: LICENSE
License-File: AUTHORS.rst
Requires-Dist: numpy
Requires-Dist: h5py
Requires-Dist: psycopg2-binary
Requires-Dist: pandas
Requires-Dist: networkx
Requires-Dist: autologging
Requires-Dist: scipy
Requires-Dist: sqlalchemy
Requires-Dist: paramiko
Requires-Dist: scikit-learn
Requires-Dist: csvsort
Requires-Dist: matplotlib
Requires-Dist: seaborn
Requires-Dist: tqdm
Requires-Dist: wget
Requires-Dist: munch
